glux/__init__.py
glux/glux.pyd
glux/glux.pyi
glux/py.typed
glux-1.0.4.dist-info/METADATA
glux-1.0.4.dist-info/WHEEL
glux-1.0.4.dist-info/top_level.txt
glux-1.0.4.dist-info/RECORD
