Metadata-Version: 2.4
Name: glux
Version: 1.0.4
Author: hashkth
Requires-Python: <3.14,>=3.11
